{"indexes":[{"v":{"$numberInt":"2"},"key":{"_id":{"$numberInt":"1"}},"name":"_id_"},{"v":{"$numberInt":"2"},"key":{"active":{"$numberInt":"1"}},"name":"active_1","background":true},{"v":{"$numberInt":"2"},"key":{"question_id":{"$numberInt":"1"}},"name":"question_id_1","background":true,"unique":true},{"v":{"$numberInt":"2"},"key":{"type":{"$numberInt":"1"}},"name":"type_1","background":true},{"v":{"$numberInt":"2"},"key":{"created_by":{"$numberInt":"1"},"type":{"$numberInt":"1"}},"name":"created_by_1_type_1","background":true},{"v":{"$numberInt":"2"},"key":{"question_id":{"$numberInt":"1"},"courses":{"$numberInt":"1"},"type":{"$numberInt":"1"}},"name":"question_id_1_courses_1_type_1","background":true},{"v":{"$numberInt":"2"},"key":{"active":{"$numberInt":"1"},"question_hindi":{"$numberInt":"1"},"chapters":{"$numberInt":"1"}},"name":"active_1_question_hindi_1_chapters_1","background":true},{"v":{"$numberInt":"2"},"key":{"question_id":{"$numberInt":"1"},"type":{"$numberInt":"1"}},"name":"question_id_1_type_1","background":true},{"v":{"$numberInt":"2"},"key":{"diff_level":{"$numberInt":"1"},"type":{"$numberInt":"1"}},"name":"diff_level_1_type_1","background":true},{"v":{"$numberInt":"2"},"key":{"language":{"$numberInt":"1"},"type":{"$numberInt":"1"}},"name":"language_1_type_1","background":true}],"uuid":"64c97c4be8df4612810572d3609bc9a2","collectionName":"questionbanks","type":"collection"}