{"indexes":[{"v":{"$numberInt":"2"},"key":{"_id":{"$numberInt":"1"}},"name":"_id_"},{"v":{"$numberInt":"2"},"key":{"active":{"$numberInt":"1"},"active_quote":{"$numberInt":"1"}},"name":"active_1_active_quote_1","background":true},{"v":{"$numberInt":"2"},"key":{"created_by":{"$numberInt":"1"}},"name":"created_by_1","background":true},{"v":{"$numberInt":"2"},"key":{"quote_en":{"$numberInt":"1"}},"name":"quote_en_1","background":true}],"uuid":"7126081c220444db896d0ee44f4e1516","collectionName":"quotes","type":"collection"}